{"id":10231,"disenchantingSkillRank":175,"description":"","name":"Engraved Cape","icon":"inv_misc_cape_18","stackable":1,"itemBind":2,"bonusStats":[],"itemSpells":[],"buyPrice":85727,"itemClass":4,"itemSubClass":1,"containerSlots":0,"inventoryType":16,"equippable":true,"itemLevel":55,"maxCount":0,"maxDurability":0,"minFactionId":0,"minReputation":0,"quality":2,"sellPrice":17145,"requiredSkill":0,"requiredLevel":50,"requiredSkillRank":0,"itemSource":{"sourceId":0,"sourceType":"NONE"},"baseArmor":7,"hasSockets":false,"isAuctionable":true,"armor":7,"displayInfoId":26278,"nameDescription":"","nameDescriptionColor":"000000","upgradable":true,"heroicTooltip":false,"context":"","bonusLists":[],"availableContexts":[""],"bonusSummary":{"defaultBonusLists":[],"chanceBonusLists":[],"bonusChances":[]}}