{"id":118794,"disenchantingSkillRank":0,"description":"","name":"Felcore Iron Wand","icon":"inv_wand_1h_draenordungeon_c_01","stackable":1,"itemBind":2,"bonusStats":[{"stat":40,"amount":28},{"stat":5,"amount":47},{"stat":36,"amount":34},{"stat":45,"amount":633},{"stat":7,"amount":71}],"itemSpells":[],"buyPrice":1503199,"itemClass":2,"itemSubClass":19,"containerSlots":0,"weaponInfo":{"damage":{"min":96,"max":180,"exactMin":96.0,"exactMax":180.0},"weaponSpeed":1.8,"dps":76.66667},"inventoryType":26,"equippable":true,"itemLevel":585,"maxCount":0,"maxDurability":90,"minFactionId":0,"minReputation":0,"quality":3,"sellPrice":300639,"requiredSkill":0,"requiredLevel":96,"requiredSkillRank":0,"itemSource":{"sourceId":0,"sourceType":"NONE"},"baseArmor":0,"hasSockets":false,"isAuctionable":true,"armor":0,"displayInfoId":136390,"nameDescription":"","nameDescriptionColor":"000000","upgradable":true,"heroicTooltip":false,"context":"","bonusLists":[],"availableContexts":[""],"bonusSummary":{"defaultBonusLists":[],"chanceBonusLists":[],"bonusChances":[]}}