{"id":118887,"disenchantingSkillRank":0,"description":"","name":"Cloudcaller's Linked Belt","icon":"inv_belt_mail_draenordungeon_c_01","stackable":1,"itemBind":2,"bonusStats":[{"stat":59,"amount":117},{"stat":49,"amount":113},{"stat":73,"amount":174},{"stat":7,"amount":260}],"itemSpells":[],"buyPrice":1148156,"itemClass":4,"itemSubClass":3,"containerSlots":0,"inventoryType":6,"equippable":true,"itemLevel":665,"maxCount":0,"maxDurability":55,"minFactionId":0,"minReputation":0,"quality":4,"sellPrice":229631,"requiredSkill":0,"requiredLevel":100,"requiredSkillRank":0,"itemSource":{"sourceId":0,"sourceType":"NONE"},"baseArmor":120,"hasSockets":false,"isAuctionable":true,"armor":120,"displayInfoId":130730,"nameDescription":"","nameDescriptionColor":"000000","upgradable":true,"heroicTooltip":false,"context":"","bonusLists":[],"availableContexts":[""],"bonusSummary":{"defaultBonusLists":[],"chanceBonusLists":[],"bonusChances":[]}}