{"id":127715,"description":"","name":"Mighty Hexweave Essence","icon":"inv_tailoringdye_red","stackable":20,"itemBind":0,"bonusStats":[],"itemSpells":[{"spellId":187502,"spell":{"id":187502,"name":"Upgrade Armor","icon":"inv_datacrystal05","description":"Upgrades item level 685 Tailoring armor to 700.","castTime":"3 sec cast"},"nCharges":1,"consumable":true,"categoryId":0,"trigger":"ON_USE"}],"buyPrice":0,"itemClass":7,"itemSubClass":11,"containerSlots":0,"inventoryType":0,"equippable":false,"itemLevel":700,"maxCount":0,"maxDurability":0,"minFactionId":0,"minReputation":0,"quality":4,"sellPrice":0,"requiredSkill":0,"requiredLevel":90,"requiredSkillRank":0,"itemSource":{"sourceId":187492,"sourceType":"CREATED_BY_SPELL"},"baseArmor":0,"hasSockets":false,"isAuctionable":true,"armor":0,"displayInfoId":0,"nameDescription":"","nameDescriptionColor":"000000","upgradable":true,"heroicTooltip":false,"context":"","bonusLists":[],"availableContexts":[""],"bonusSummary":{"defaultBonusLists":[],"chanceBonusLists":[],"bonusChances":[]}}