{"id":13043,"disenchantingSkillRank":150,"description":"","name":"Blade of the Titans","icon":"inv_sword_07","stackable":1,"itemBind":2,"bonusStats":[{"stat":4,"amount":9},{"stat":7,"amount":21}],"itemSpells":[],"buyPrice":161949,"itemClass":2,"itemSubClass":8,"containerSlots":0,"weaponInfo":{"damage":{"min":60,"max":90,"exactMin":60.0,"exactMax":90.0},"weaponSpeed":3.3,"dps":22.727274},"inventoryType":17,"equippable":true,"itemLevel":49,"maxCount":0,"maxDurability":100,"minFactionId":0,"minReputation":0,"quality":3,"sellPrice":32389,"requiredSkill":0,"requiredLevel":44,"requiredSkillRank":0,"itemSource":{"sourceId":0,"sourceType":"NONE"},"baseArmor":0,"hasSockets":false,"isAuctionable":true,"armor":0,"displayInfoId":28675,"nameDescription":"","nameDescriptionColor":"000000","upgradable":true,"heroicTooltip":false,"context":"","bonusLists":[],"availableContexts":[""],"bonusSummary":{"defaultBonusLists":[],"chanceBonusLists":[],"bonusChances":[]}}