{"id":13081,"disenchantingSkillRank":100,"description":"","name":"Skullance Shield","icon":"inv_shield_02","stackable":1,"itemBind":2,"bonusStats":[{"stat":4,"amount":7},{"stat":3,"amount":4},{"stat":7,"amount":5}],"itemSpells":[],"buyPrice":35618,"itemClass":4,"itemSubClass":6,"containerSlots":0,"inventoryType":14,"equippable":true,"itemLevel":38,"maxCount":0,"maxDurability":100,"minFactionId":0,"minReputation":0,"quality":3,"sellPrice":7123,"requiredSkill":0,"requiredLevel":33,"requiredSkillRank":0,"itemSource":{"sourceId":0,"sourceType":"NONE"},"baseArmor":104,"hasSockets":false,"isAuctionable":true,"armor":104,"displayInfoId":18790,"nameDescription":"","nameDescriptionColor":"000000","upgradable":true,"heroicTooltip":false,"context":"","bonusLists":[],"availableContexts":[""],"bonusSummary":{"defaultBonusLists":[],"chanceBonusLists":[],"bonusChances":[]}}