{"id":15670,"disenchantingSkillRank":225,"description":"","name":"Magnificent Helmet","icon":"inv_helmet_12","stackable":1,"itemBind":2,"bonusStats":[],"itemSpells":[],"buyPrice":115011,"itemClass":4,"itemSubClass":3,"containerSlots":0,"inventoryType":1,"equippable":true,"itemLevel":61,"maxCount":0,"maxDurability":70,"minFactionId":0,"minReputation":0,"quality":2,"sellPrice":23002,"requiredSkill":0,"requiredLevel":56,"requiredSkillRank":0,"itemSource":{"sourceId":0,"sourceType":"NONE"},"baseArmor":27,"hasSockets":false,"isAuctionable":true,"armor":27,"displayInfoId":16413,"nameDescription":"","nameDescriptionColor":"000000","upgradable":true,"heroicTooltip":false,"context":"","bonusLists":[],"availableContexts":[""],"bonusSummary":{"defaultBonusLists":[],"chanceBonusLists":[],"bonusChances":[]}}