{"id":23427,"description":"","name":"Eternium Ore","icon":"inv_ore_eternium","stackable":200,"itemBind":0,"bonusStats":[],"itemSpells":[],"buyPrice":5000,"itemClass":7,"itemSubClass":7,"containerSlots":0,"inventoryType":0,"equippable":false,"itemLevel":70,"maxCount":0,"maxDurability":0,"minFactionId":0,"minReputation":0,"quality":2,"sellPrice":1250,"requiredSkill":0,"requiredLevel":0,"requiredSkillRank":0,"itemSource":{"sourceId":153820,"sourceType":"CREATED_BY_SPELL"},"baseArmor":0,"hasSockets":false,"isAuctionable":true,"armor":0,"displayInfoId":0,"nameDescription":"","nameDescriptionColor":"000000","upgradable":true,"heroicTooltip":false,"context":"","bonusLists":[],"availableContexts":[""],"bonusSummary":{"defaultBonusLists":[],"chanceBonusLists":[],"bonusChances":[]}}