{"id":24769,"disenchantingSkillRank":275,"description":"","name":"Clefthoof Cover","icon":"inv_helmet_43","stackable":1,"itemBind":2,"bonusStats":[],"itemSpells":[],"buyPrice":189839,"itemClass":4,"itemSubClass":2,"containerSlots":0,"inventoryType":1,"equippable":true,"itemLevel":108,"maxCount":0,"maxDurability":70,"minFactionId":0,"minReputation":0,"quality":2,"sellPrice":37967,"requiredSkill":0,"requiredLevel":66,"requiredSkillRank":0,"itemSource":{"sourceId":184936,"sourceType":"GAME_OBJECT_DROP"},"baseArmor":21,"hasSockets":false,"isAuctionable":true,"armor":21,"displayInfoId":142038,"nameDescription":"","nameDescriptionColor":"000000","upgradable":true,"heroicTooltip":false,"context":"","bonusLists":[],"availableContexts":[""],"bonusSummary":{"defaultBonusLists":[],"chanceBonusLists":[],"bonusChances":[]}}