{"id":31333,"disenchantingSkillRank":300,"description":"","name":"The Night Watchman","icon":"inv_helmet_43","stackable":1,"itemBind":2,"bonusStats":[{"stat":3,"amount":26},{"stat":7,"amount":35}],"itemSpells":[{"spellId":23217,"spell":{"id":23217,"name":"Stealth Detection","icon":"ability_eyeoftheowl","description":"Slightly increases your stealth detection.","castTime":"Passive"},"nCharges":0,"consumable":false,"categoryId":0,"trigger":"ON_EQUIP"}],"buyPrice":280601,"itemClass":4,"itemSubClass":2,"containerSlots":0,"inventoryType":1,"equippable":true,"itemLevel":100,"maxCount":0,"maxDurability":100,"minFactionId":0,"minReputation":0,"quality":4,"sellPrice":56120,"requiredSkill":0,"requiredLevel":70,"requiredSkillRank":0,"itemSource":{"sourceId":0,"sourceType":"NONE"},"baseArmor":20,"hasSockets":false,"isAuctionable":true,"armor":20,"displayInfoId":45167,"nameDescription":"","nameDescriptionColor":"000000","upgradable":true,"heroicTooltip":false,"context":"","bonusLists":[],"availableContexts":[""],"bonusSummary":{"defaultBonusLists":[],"chanceBonusLists":[],"bonusChances":[]}}