{"id":3306,"disenchantingSkillRank":1,"description":"","name":"Brackwater Vest","icon":"inv_chest_cloth_06","stackable":1,"itemBind":2,"bonusStats":[{"stat":4,"amount":4},{"stat":7,"amount":3}],"itemSpells":[],"buyPrice":3814,"itemClass":4,"itemSubClass":3,"containerSlots":0,"inventoryType":5,"equippable":true,"itemLevel":18,"maxCount":0,"maxDurability":90,"minFactionId":0,"minReputation":0,"quality":2,"sellPrice":762,"requiredSkill":0,"requiredLevel":13,"requiredSkillRank":0,"itemSource":{"sourceId":0,"sourceType":"NONE"},"baseArmor":15,"hasSockets":false,"isAuctionable":true,"armor":15,"displayInfoId":25238,"nameDescription":"","nameDescriptionColor":"000000","upgradable":true,"heroicTooltip":false,"context":"","bonusLists":[],"availableContexts":[""],"bonusSummary":{"defaultBonusLists":[],"chanceBonusLists":[],"bonusChances":[]}}