{"id":36394,"disenchantingSkillRank":350,"description":"","name":"Revenant Bracers","icon":"inv_bracer_10","stackable":1,"itemBind":2,"bonusStats":[],"itemSpells":[],"buyPrice":202484,"itemClass":4,"itemSubClass":4,"containerSlots":0,"inventoryType":9,"equippable":true,"itemLevel":178,"maxCount":0,"maxDurability":40,"minFactionId":0,"minReputation":0,"quality":2,"sellPrice":40496,"requiredSkill":0,"requiredLevel":79,"requiredSkillRank":0,"itemSource":{"sourceId":0,"sourceType":"NONE"},"baseArmor":32,"hasSockets":false,"isAuctionable":true,"armor":32,"displayInfoId":51905,"nameDescription":"","nameDescriptionColor":"000000","upgradable":true,"heroicTooltip":false,"context":"","bonusLists":[],"availableContexts":[""],"bonusSummary":{"defaultBonusLists":[],"chanceBonusLists":[],"bonusChances":[]}}