{"id":37755,"disenchantingSkillRank":325,"description":"","name":"Leggings of the Icy Heart","icon":"inv_pants_cloth_11","stackable":1,"itemBind":2,"bonusStats":[{"stat":32,"amount":17},{"stat":5,"amount":20},{"stat":6,"amount":21},{"stat":7,"amount":30}],"itemSpells":[],"buyPrice":380428,"itemClass":4,"itemSubClass":1,"containerSlots":0,"inventoryType":7,"equippable":true,"itemLevel":146,"maxCount":0,"maxDurability":100,"minFactionId":0,"minReputation":0,"quality":3,"sellPrice":76085,"requiredSkill":0,"requiredLevel":73,"requiredSkillRank":0,"itemSource":{"sourceId":207479,"sourceType":"GAME_OBJECT_DROP"},"baseArmor":15,"hasSockets":false,"isAuctionable":true,"armor":15,"displayInfoId":52472,"nameDescription":"","nameDescriptionColor":"000000","upgradable":true,"heroicTooltip":false,"context":"","bonusLists":[],"availableContexts":[""],"bonusSummary":{"defaultBonusLists":[],"chanceBonusLists":[],"bonusChances":[]}}