{"id":45927,"disenchantingSkillRank":375,"description":"","name":"Handwraps of Resonance","icon":"inv_gauntlets_55","stackable":1,"itemBind":2,"bonusStats":[{"stat":32,"amount":14},{"stat":5,"amount":23},{"stat":6,"amount":14},{"stat":7,"amount":31}],"itemSpells":[],"buyPrice":387542,"itemClass":4,"itemSubClass":1,"containerSlots":0,"inventoryType":10,"equippable":true,"itemLevel":219,"maxCount":0,"maxDurability":55,"minFactionId":0,"minReputation":0,"quality":4,"sellPrice":77508,"requiredSkill":0,"requiredLevel":80,"requiredSkillRank":0,"itemSource":{"sourceId":194312,"sourceType":"GAME_OBJECT_DROP"},"baseArmor":12,"hasSockets":false,"isAuctionable":true,"armor":12,"displayInfoId":59719,"nameDescription":"","nameDescriptionColor":"000000","upgradable":true,"heroicTooltip":false,"context":"","bonusLists":[],"availableContexts":[""],"bonusSummary":{"defaultBonusLists":[],"chanceBonusLists":[],"bonusChances":[]}}