{"id":5071,"disenchantingSkillRank":1,"description":"","name":"Shadow Wand","icon":"inv_weapon_shortblade_09","stackable":1,"itemBind":2,"bonusStats":[],"itemSpells":[],"buyPrice":2215,"itemClass":2,"itemSubClass":19,"containerSlots":0,"weaponInfo":{"damage":{"min":2,"max":5,"exactMin":2.0,"exactMax":5.0},"weaponSpeed":1.8,"dps":1.9444445},"inventoryType":26,"equippable":true,"itemLevel":14,"maxCount":0,"maxDurability":45,"minFactionId":0,"minReputation":0,"quality":2,"sellPrice":443,"requiredSkill":0,"requiredLevel":9,"requiredSkillRank":0,"itemSource":{"sourceId":0,"sourceType":"NONE"},"baseArmor":0,"hasSockets":false,"isAuctionable":true,"armor":0,"displayInfoId":18356,"nameDescription":"","nameDescriptionColor":"000000","upgradable":true,"heroicTooltip":false,"context":"","bonusLists":[],"availableContexts":[""],"bonusSummary":{"defaultBonusLists":[],"chanceBonusLists":[],"bonusChances":[]}}