{"id":9964,"disenchantingSkillRank":150,"description":"","name":"Warmonger's Leggings","icon":"inv_pants_06","stackable":1,"itemBind":2,"bonusStats":[],"itemSpells":[],"buyPrice":76944,"itemClass":4,"itemSubClass":3,"containerSlots":0,"inventoryType":7,"equippable":true,"itemLevel":49,"maxCount":0,"maxDurability":85,"minFactionId":0,"minReputation":0,"quality":2,"sellPrice":15388,"requiredSkill":0,"requiredLevel":44,"requiredSkillRank":0,"itemSource":{"sourceId":176944,"sourceType":"GAME_OBJECT_DROP"},"baseArmor":25,"hasSockets":false,"isAuctionable":true,"armor":25,"displayInfoId":11285,"nameDescription":"","nameDescriptionColor":"000000","upgradable":true,"heroicTooltip":false,"context":"","bonusLists":[],"availableContexts":[""],"bonusSummary":{"defaultBonusLists":[],"chanceBonusLists":[],"bonusChances":[]}}