{"lastModified":1422372539000,"name":"Goblyncoln","realm":"Sargeras","battlegroup":"Embuscade / Hinterhalt","class":9,"race":9,"gender":0,"level":86,"achievementPoints":5470,"thumbnail":"garona/145/89546129-avatar.jpg","calcClass":"V","items":{"averageItemLevel":354,"averageItemLevelEquipped":351,"head":{"id":90289,"name":"Peacebreaker's Silk Cowl","icon":"inv_helmet_102","quality":2,"itemLevel":372,"tooltipParams":{"timewalkerLevel":86},"stats":[{"stat":32,"amount":21},{"stat":5,"amount":28},{"stat":36,"amount":16},{"stat":7,"amount":43}],"armor":16,"context":"quest-reward","bonusLists":[]},"neck":{"id":57275,"name":"Hyjal Savior's Pendant","icon":"inv_misc_necklacea11","quality":3,"itemLevel":288,"tooltipParams":{"timewalkerLevel":86},"stats":[{"stat":32,"amount":11},{"stat":5,"amount":15},{"stat":6,"amount":9},{"stat":7,"amount":23}],"armor":0,"context":"quest-reward","bonusLists":[]},"shoulder":{"id":61444,"name":"Bondshatter Shoulders","icon":"inv_shoulder_cloth_cataclysm_b_01","quality":2,"itemLevel":305,"tooltipParams":{"timewalkerLevel":86},"stats":[{"stat":49,"amount":15},{"stat":32,"amount":14},{"stat":5,"amount":22},{"stat":7,"amount":32}],"armor":15,"context":"quest-reward","bonusLists":[]},"back":{"id":88702,"name":"Wikket Cloak","icon":"inv_cape_pandaria_b_01","quality":2,"itemLevel":384,"tooltipParams":{"timewalkerLevel":86},"stats":[{"stat":49,"amount":11},{"stat":32,"amount":10},{"stat":5,"amount":16},{"stat":7,"amount":24}],"armor":10,"context":"quest-reward","bonusLists":[]},"chest":{"id":80708,"name":"Silkwood Robe","icon":"inv_chest_cloth_panda_b_02","quality":2,"itemLevel":384,"tooltipParams":{"timewalkerLevel":86},"stats":[{"stat":49,"amount":20},{"stat":32,"amount":18},{"stat":5,"amount":29},{"stat":7,"amount":43}],"armor":20,"context":"quest-reward","bonusLists":[]},"wrist":{"id":80753,"name":"Silkwood Cuffs","icon":"inv_bracer_cloth_panda_b_02","quality":2,"itemLevel":384,"tooltipParams":{"timewalkerLevel":86},"stats":[{"stat":49,"amount":11},{"stat":32,"amount":11},{"stat":5,"amount":16},{"stat":7,"amount":24}],"armor":9,"context":"quest-reward","bonusLists":[]},"hands":{"id":61453,"name":"Gloves of Troggslaying","icon":"inv_gauntlets_cloth_cataclysm_b_01","quality":2,"itemLevel":305,"tooltipParams":{"timewalkerLevel":86},"stats":[{"stat":32,"amount":11},{"stat":5,"amount":22},{"stat":36,"amount":16},{"stat":7,"amount":32}],"armor":12,"context":"quest-reward","bonusLists":[]},"waist":{"id":61397,"name":"Pillarbind Waistguard","icon":"inv_belt_robe_dungeonrobe_c_03","quality":3,"itemLevel":318,"tooltipParams":{"timewalkerLevel":86},"stats":[{"stat":49,"amount":14},{"stat":5,"amount":22},{"stat":36,"amount":14},{"stat":7,"amount":32}],"armor":11,"context":"quest-reward","bonusLists":[]},"legs":{"id":90307,"name":"Honorary Combat Engineer's Satin Leggings","icon":"inv_pants_cloth_06","quality":2,"itemLevel":372,"tooltipParams":{"timewalkerLevel":86},"stats":[{"stat":49,"amount":16},{"stat":32,"amount":21},{"stat":5,"amount":28},{"stat":7,"amount":43}],"armor":18,"context":"quest-reward","bonusLists":[]},"feet":{"id":90315,"name":"Landfall Silk Treads","icon":"inv_boots_cloth_17","quality":2,"itemLevel":372,"tooltipParams":{"timewalkerLevel":86},"stats":[{"stat":49,"amount":11},{"stat":32,"amount":16},{"stat":5,"amount":22},{"stat":7,"amount":32}],"armor":14,"context":"quest-reward","bonusLists":[]},"finger1":{"id":88707,"name":"Windfur Ring","icon":"inv_jewelry_ring_123","quality":2,"itemLevel":384,"tooltipParams":{"timewalkerLevel":86},"stats":[{"stat":32,"amount":10},{"stat":5,"amount":16},{"stat":36,"amount":11},{"stat":7,"amount":24}],"armor":0,"context":"quest-reward","bonusLists":[]},"finger2":{"id":80769,"name":"Serpentspine Band","icon":"inv_jewelry_ring_120","quality":2,"itemLevel":384,"tooltipParams":{"timewalkerLevel":86},"stats":[{"stat":49,"amount":11},{"stat":32,"amount":11},{"stat":5,"amount":16},{"stat":7,"amount":24}],"armor":0,"context":"quest-reward","bonusLists":[]},"trinket1":{"id":73109,"name":"Dreadsoul Idol of Destruction","icon":"inv_qirajidol_sun","quality":2,"itemLevel":232,"tooltipParams":{"timewalkerLevel":86},"stats":[{"stat":49,"amount":23}],"armor":0,"context":"","bonusLists":[]},"trinket2":{"id":82984,"name":"Jade Raccoon","icon":"inv_jewelcrafting_emeraldhare","quality":2,"itemLevel":384,"tooltipParams":{"timewalkerLevel":86},"stats":[{"stat":49,"amount":27}],"armor":0,"context":"quest-reward","bonusLists":[]},"mainHand":{"id":80789,"name":"Jinyu Divining Rod","icon":"inv_staff_2h_pandariaquest_b_03","quality":3,"itemLevel":404,"tooltipParams":{"timewalkerLevel":86},"stats":[{"stat":49,"amount":23},{"stat":32,"amount":19},{"stat":5,"amount":32},{"stat":7,"amount":48},{"stat":45,"amount":184}],"armor":0,"weaponInfo":{"damage":{"min":76,"max":115,"exactMin":76.0,"exactMax":115.0},"weaponSpeed":3.3,"dps":28.939394},"context":"quest-reward","bonusLists":[]}},"totalHonorableKills":1}